Metadata-Version: 2.1
Name: shot-scraper-test
Version: 0.9
Summary: Tools for taking automated screenshots of websites
Home-page: https://github.com/simonw/shot-scraper
Author: Simon Willison
License: Apache License, Version 2.0
Project-URL: Issues, https://github.com/simonw/shot-scraper/issues
Project-URL: CI, https://github.com/simonw/shot-scraper/actions
Project-URL: Changelog, https://github.com/simonw/shot-scraper/releases
Platform: UNKNOWN
Requires-Python: >=3.7
Provides-Extra: test
